mlserver_alibi_explain/__init__.py
mlserver_alibi_explain/alibi_dependency_reference.py
mlserver_alibi_explain/common.py
mlserver_alibi_explain/errors.py
mlserver_alibi_explain/explainers/__init__.py
mlserver_alibi_explain/explainers/black_box_runtime.py
mlserver_alibi_explain/explainers/integrated_gradients.py
mlserver_alibi_explain/explainers/sklearn_api_runtime.py
mlserver_alibi_explain/explainers/white_box_runtime.py
mlserver_alibi_explain/runtime.py
mlserver_alibi_explain/version.py
mlserver_alibi_explain-1.6.1.dist-info/LICENSE
mlserver_alibi_explain-1.6.1.dist-info/METADATA
mlserver_alibi_explain-1.6.1.dist-info/WHEEL
mlserver_alibi_explain-1.6.1.dist-info/RECORD
